pyctlib/__init__.py
pyctlib/basicwrapper.py
pyctlib/classfunc.py
pyctlib/filemanager.py
pyctlib/logging.py
pyctlib/strtools.py
pyctlib/terminal.py
pyctlib/test_curses.py
pyctlib/timing.py
pyctlib/touch.py
pyctlib/vector.py
pyctlib/wrapper.py
pyctlib/visual/__init__.py
pyctlib/visual/debugger.py
pyctlib/visual/display.py
pyctlib/visual/plot.py
pyctlib/visual/progress.py
pyctlib-0.3.127.dist-info/METADATA
pyctlib-0.3.127.dist-info/WHEEL
pyctlib-0.3.127.dist-info/top_level.txt
pyctlib-0.3.127.dist-info/RECORD
