Metadata-Version: 2.1
Name: pyctlib
Version: 0.3.127
Summary: This is A foundamental package containing some basic self-designed functions and types for Project PyCTLib. 
Home-page: https://github.com/Bertie97/pyctlib/tree/main/pyctlib
Author: All contributors of PyCTLib
Author-email: 2247501256@qq.com
License: MIT Licence
Keywords: pip,pyctlib
Platform: any
Requires-Dist: pyoverload
Requires-Dist: rapidfuzz
Requires-Dist: numpy
Requires-Dist: wrapt-timeout-decorator
Requires-Dist: notion
